MANIFEST.in
README.rst
setup.py
src/fise/__init__.py
src/fise.plone.egg-info/PKG-INFO
src/fise.plone.egg-info/SOURCES.txt
src/fise.plone.egg-info/dependency_links.txt
src/fise.plone.egg-info/entry_points.txt
src/fise.plone.egg-info/namespace_packages.txt
src/fise.plone.egg-info/requires.txt
src/fise.plone.egg-info/top_level.txt
src/fise.plone.egg-info/zip-safe
src/fise/plone/__init__.py
src/fise/plone/browser.py
src/fise/plone/configure.zcml
src/fise/plone/profiles.zcml
src/fise/plone/subscribers.py
src/fise/plone/utils.py
src/fise/plone/profile/actions.xml
src/fise/plone/profile/browserlayer.xml
src/fise/plone/profile/metadata.xml
src/fise/plone/profile/propertiestool.xml
src/fise/plone/templates/enhancements.pt
src/fise/plone/templates/raw.pt