Metadata-Version: 1.0
Name: fise.plone
Version: 0.3
Summary: Stanbol FISE Semantic Engine: RESTful Plone Integration.
Home-page: UNKNOWN
Author: Jens Klein    
Author-email: jens@bluedynamics.com
License: GPLv2
Platform: UNKNOWN
Classifier: Development Status :: 5 - Production/Stable
Classifier: License :: OSI Approved :: GNU General Public License (GPL)
Classifier: Operating System :: OS Independent
Classifier: Programming Language :: Python
Classifier: Topic :: Software Development
